SPEMM/__init__.py
SPEMM/comp.py
SPEMM/main.py
SPEMM/metrics.py
SPEMM/utils.py
SPEMM-1.1.9.dist-info/METADATA
SPEMM-1.1.9.dist-info/RECORD
SPEMM-1.1.9.dist-info/WHEEL
SPEMM-1.1.9.dist-info/entry_points.txt
SPEMM-1.1.9.dist-info/top_level.txt
SPEMM-1.1.9.dist-info/zip-safe
